MANIFEST.in
setup.cfg
setup.py
stratus_api/integrations/__init__.py
stratus_api/integrations/base.py
stratus_api/integrations/cache.py
stratus_api/integrations/chunks.py
stratus_api/integrations/distribution.py
stratus_api/integrations/exceptions.py
stratus_api/integrations/routes/__init__.py
stratus_api/integrations/routes/v1/__init__.py
stratus_api/integrations/routes/v1/destinations.py
stratus_api/integrations/routes/v1/distribution.py
stratus_api/integrations/routes/v1/performances.py
stratus_api/integrations/routes/v1/segments.py
stratus_api/integrations/routes/v1/settings.py
stratus_api/integrations/schemas/v1.yaml
stratus_api/integrations/tasks/__init__.py
stratus_api/integrations/tasks/distributions.py
stratus_api/integrations/tasks/performances.py
stratus_api_integrations_pubsub.egg-info/PKG-INFO
stratus_api_integrations_pubsub.egg-info/SOURCES.txt
stratus_api_integrations_pubsub.egg-info/dependency_links.txt
stratus_api_integrations_pubsub.egg-info/requires.txt
stratus_api_integrations_pubsub.egg-info/top_level.txt