Metadata-Version: 2.1
Name: stratus-api-integrations-pubsub
Version: 0.0.1
Summary: Simplified advertising integrations using pubsub
Home-page: https://bitbucket.org/adarainc/stratus-api-integrations-pubsub
Author: DOT
Author-email: dot@adara.com
Classifier: Programming Language :: Python :: 3
Classifier: License :: OSI Approved :: MIT License
Classifier: Operating System :: OS Independent
Requires-Python: >=3.11
